pyjsonec/EscapeCompression.py
pyjsonec/__init__.py
pyjsonec-0.0.1.dist-info/LICENSE
pyjsonec-0.0.1.dist-info/METADATA
pyjsonec-0.0.1.dist-info/WHEEL
pyjsonec-0.0.1.dist-info/top_level.txt
pyjsonec-0.0.1.dist-info/RECORD
