Metadata-Version: 2.1
Name: pyjsonec
Version: 0.0.1
Summary: InterfaceUseCaseParameterExplosion
Home-page: https://github.com/Duchongc/pyjsonec
Author: Anran
Author-email: 1978529954@qq.com
License: UNKNOWN
Platform: UNKNOWN
Classifier: Programming Language :: Python :: 3
Classifier: License :: OSI Approved :: MIT License
Classifier: Operating System :: OS Independent
Requires-Python: >=3.6
